README.rst
setup.py
slckbt/__init__.py
slckbt/base.py
slckbt.egg-info/PKG-INFO
slckbt.egg-info/SOURCES.txt
slckbt.egg-info/dependency_links.txt
slckbt.egg-info/not-zip-safe
slckbt.egg-info/requires.txt
slckbt.egg-info/top_level.txt