Metadata-Version: 1.0
Name: slckbt
Version: 0.1
Summary: Basic chat bot for Slack
Home-page: http://github.com/pannkotsky/slckbt
Author: Valerii Kovalchuk
Author-email: kovvalole@gmail.com
License: MIT
Platform: UNKNOWN
